vapordmods/__init__.py
vapordmods/api/__init__.py
vapordmods/api/base.py
vapordmods/api/github.py
vapordmods/api/nexusmods.py
vapordmods/api/thunderstore.py
vapordmods/api/worhshop.py
vapordmods/mods/__init__.py
vapordmods/mods/modsmanager.py
vapordmods/mods/schema.py
vapordmods/tools/__init__.py
vapordmods/tools/steamcmd.py
vapordmods/tools/utils.py
vapordmods-0.2.6.dist-info/LICENSE
vapordmods-0.2.6.dist-info/METADATA
vapordmods-0.2.6.dist-info/WHEEL
vapordmods-0.2.6.dist-info/top_level.txt
vapordmods-0.2.6.dist-info/RECORD
