Metadata-Version: 2.1
Name: vapordmods
Version: 0.2.6
Summary: Manage multiples mods provider: Thunderstore, Nexismods, Seam Workshop and Github.
Home-page: https://github.com/FireFollet/vapordmods
Author: FireFollet
Author-email: 
License: MIT
Project-URL: Bug Tracker, https://github.com/FireFollet/vapordmods/issues
Classifier: Development Status :: 3 - Alpha
Classifier: Intended Audience :: Developers
Classifier: License :: OSI Approved :: MIT License
Classifier: Programming Language :: Python :: 3.8
Classifier: Programming Language :: Python :: 3.9
Classifier: Programming Language :: Python :: 3.10
Requires-Python: >=3.8
License-File: LICENSE
Requires-Dist: PyYAML (~=6.0)
Requires-Dist: aiohttp (~=3.8.1)
Requires-Dist: aiofiles (~=0.8.0)
Requires-Dist: pandas (~=1.4.2)
Requires-Dist: cerberus (~=1.3.4)
